my_own_package/__init__.py
oana_first_package-0.1.0.dist-info/METADATA
oana_first_package-0.1.0.dist-info/WHEEL
oana_first_package-0.1.0.dist-info/top_level.txt
oana_first_package-0.1.0.dist-info/RECORD
