Metadata-Version: 2.1
Name: oana-first-package
Version: 0.1.0
Summary: my_first_package
Author: Oana Iliescu
